<annotation>
	<folder>resize</folder>
	<filename>multiple_object (105).JPG</filename>
	<path>D:\ECODO\resize\multiple_object (105).JPG</path>
	<source>
		<database>Unknown</database>
	</source>
	<size>
		<width>300</width>
		<height>300</height>
		<depth>3</depth>
	</size>
	<segmented>0</segmented>
	<object>
		<name>glass</name>
		<pose>Unspecified</pose>
		<truncated>0</truncated>
		<difficult>0</difficult>
		<bndbox>
			<xmin>71</xmin>
			<ymin>100</ymin>
			<xmax>116</xmax>
			<ymax>145</ymax>
		</bndbox>
	</object>
	<object>
		<name>glass</name>
		<pose>Unspecified</pose>
		<truncated>0</truncated>
		<difficult>0</difficult>
		<bndbox>
			<xmin>47</xmin>
			<ymin>110</ymin>
			<xmax>85</xmax>
			<ymax>160</ymax>
		</bndbox>
	</object>
	<object>
		<name>plastic bottle</name>
		<pose>Unspecified</pose>
		<truncated>0</truncated>
		<difficult>0</difficult>
		<bndbox>
			<xmin>189</xmin>
			<ymin>137</ymin>
			<xmax>235</xmax>
			<ymax>161</ymax>
		</bndbox>
	</object>
	<object>
		<name>glass</name>
		<pose>Unspecified</pose>
		<truncated>1</truncated>
		<difficult>0</difficult>
		<bndbox>
			<xmin>283</xmin>
			<ymin>128</ymin>
			<xmax>300</xmax>
			<ymax>177</ymax>
		</bndbox>
	</object>
</annotation>
